maclocate
