Metadata-Version: 1.0
Name: maclocate
Version: 0.1.5
Summary: Python interface to the SkyHook wireless API
Home-page: http://maclocate.googlecode.com
Author: Ian McCracken
Author-email: ian.mccracken@gmail.com
License: MIT License
Platform: UNKNOWN
